pyproject.toml
src/deb/debutils.py
src/sdk_deb.egg-info/PKG-INFO
src/sdk_deb.egg-info/SOURCES.txt
src/sdk_deb.egg-info/dependency_links.txt
src/sdk_deb.egg-info/requires.txt
src/sdk_deb.egg-info/top_level.txt