Metadata-Version: 2.1
Name: sdk-deb
Version: 0.0.0
Author: Pemrilect
Author-email: 49397056@qq.com
Requires-Python: >=3.1.0
Requires-Dist: devkit-list>=2024.2
